llmtree/__init__.py
llmtree/cli.py
llmtree-1.0.1.dist-info/METADATA
llmtree-1.0.1.dist-info/WHEEL
llmtree-1.0.1.dist-info/entry_points.txt
llmtree-1.0.1.dist-info/top_level.txt
llmtree-1.0.1.dist-info/RECORD
